apubsub/__init__.py
apubsub/client.py
apubsub/connection_wrapper.py
apubsub/protocol.py
apubsub/server.py
apubsub-0.2.5.dist-info/LICENSE
apubsub-0.2.5.dist-info/WHEEL
apubsub-0.2.5.dist-info/METADATA
apubsub-0.2.5.dist-info/RECORD
