Metadata-Version: 2.1
Name: apubsub
Version: 0.2.5
Summary: Message service implementing publisher/subscriber pattern
Home-page: https://github.com/outcatcher/apubsub
License: MIT
Author: Anton Kachurin
Author-email: katchuring@gmail.com
Requires-Python: >=3.7,<4.0
Classifier: License :: OSI Approved :: MIT License
Classifier: Programming Language :: Python :: 3
Classifier: Programming Language :: Python :: 3.7
Classifier: Programming Language :: Python :: 3.8
Classifier: Programming Language :: Python :: 3.9
Requires-Dist: uvloop (>=0.14.0,<0.15.0); sys_platform == "linux"
Project-URL: Repository, https://github.com/outcatcher/apubsub
